Metadata-Version: 2.1
Name: fantasy-premier-league-stats
Version: 0.0.2
Summary: Stats and Visualizations for FPL, Fantasy Allsvenskan and Fantasy Eliteserien
Home-page: https://github.com/goktugerce/fantasy-premier-league
Author: Göktuğ Erce Gürel
Author-email: goktugercegurel@gmail.com
License: UNKNOWN
Platform: UNKNOWN
Classifier: Programming Language :: Python :: 3.6
Classifier: Programming Language :: Python :: 3.7
Classifier: License :: OSI Approved :: MIT License
Classifier: Operating System :: OS Independent
Requires-Dist: requests
Requires-Dist: jsonpickle
Requires-Dist: pandas
Requires-Dist: matplotlib
Requires-Dist: seaborn
Requires-Dist: Pillow
